robobase/__init__.py
robobase/converters.py
robobase/dhmatrix.py
robobase/forwardkinematics.py
robobase/potensialfield.py
robobase/quaternion.py
robobase/quaternionfunctions.py
robobase/rotate.py
robobase/routeA.py
robobase/routecommon.py
robobase/routedijkstra.py
robobase/speedkinematics.py
robobase/trianglealg.py
robobase_package-1.0.0.dist-info/LICENSE
robobase_package-1.0.0.dist-info/METADATA
robobase_package-1.0.0.dist-info/WHEEL
robobase_package-1.0.0.dist-info/top_level.txt
robobase_package-1.0.0.dist-info/RECORD
