Metadata-Version: 2.1
Name: robobase-package
Version: 1.0.0
Summary: Package for basic robotic analysis
Home-page: https://github.com/Ilya-Belyanov/robobase
Author: Ilya Belyanov
Author-email: belyanov.99@mail.ru
License: UNKNOWN
Project-URL: Bug Tracker, https://github.com/Ilya-Belyanov/robobase/issues
Platform: UNKNOWN
Classifier: Programming Language :: Python :: 3
Classifier: License :: OSI Approved :: MIT License
Classifier: Operating System :: OS Independent
Requires-Python: >=3.6
License-File: LICENSE
